ewah/__init__.py
ewah/cleaner.py
ewah/constants/__init__.py
ewah/dag_factories/__init__.py
ewah/dag_factories/dag_factory_atomic.py
ewah/dag_factories/dag_factory_idempotent.py
ewah/dag_factories/dag_factory_mixed.py
ewah/dag_factories/dbt_dag_factory.py
ewah/hooks/__init__.py
ewah/hooks/aircall.py
ewah/hooks/airflow.py
ewah/hooks/airtable.py
ewah/hooks/amazon_ads.py
ewah/hooks/amazon_seller_central.py
ewah/hooks/aws.py
ewah/hooks/base.py
ewah/hooks/bigquery.py
ewah/hooks/braze.py
ewah/hooks/dbt_env_var.py
ewah/hooks/facebook.py
ewah/hooks/git.py
ewah/hooks/google_ads.py
ewah/hooks/google_analytics.py
ewah/hooks/google_cloud_storage.py
ewah/hooks/hubspot.py
ewah/hooks/infigo.py
ewah/hooks/linkedin.py
ewah/hooks/mailchimp.py
ewah/hooks/metabase.py
ewah/hooks/mongodb.py
ewah/hooks/mssql.py
ewah/hooks/mysql.py
ewah/hooks/oracle.py
ewah/hooks/personio.py
ewah/hooks/pipedrive.py
ewah/hooks/plentymarkets.py
ewah/hooks/postgres.py
ewah/hooks/rapidmail.py
ewah/hooks/recurly.py
ewah/hooks/salesforce.py
ewah/hooks/sevdesk.py
ewah/hooks/sharepoint.py
ewah/hooks/shopify.py
ewah/hooks/shopify_graphql.py
ewah/hooks/snowflake.py
ewah/hooks/sql_base.py
ewah/hooks/ssh.py
ewah/hooks/stripe.py
ewah/operators/__init__.py
ewah/operators/aircall.py
ewah/operators/airflow.py
ewah/operators/airtable.py
ewah/operators/amazon_ads.py
ewah/operators/amazon_seller_central.py
ewah/operators/base.py
ewah/operators/braze.py
ewah/operators/dynamodb.py
ewah/operators/facebook.py
ewah/operators/fx.py
ewah/operators/fx_yfinance.py
ewah/operators/google_ads.py
ewah/operators/google_analytics.py
ewah/operators/google_cloud_storage.py
ewah/operators/google_maps.py
ewah/operators/google_sheets.py
ewah/operators/hubspot.py
ewah/operators/infigo.py
ewah/operators/linkedin.py
ewah/operators/linkedin_ads.py
ewah/operators/mailchimp.py
ewah/operators/mailingwork.py
ewah/operators/mongodb.py
ewah/operators/personio.py
ewah/operators/pipedrive.py
ewah/operators/plentymarkets.py
ewah/operators/rapidmail.py
ewah-0.9.21.dist-info/LICENSE
ewah-0.9.21.dist-info/METADATA
ewah-0.9.21.dist-info/WHEEL
ewah-0.9.21.dist-info/entry_points.txt
ewah-0.9.21.dist-info/top_level.txt
ewah-0.9.21.dist-info/RECORD
