Metadata-Version: 2.1
Name: ewah
Version: 0.9.21
Summary: An ELT with airflow helper module: Ewah
Home-page: https://gemmaanalytics.com/
Author: Bijan Soltani
Author-email: bijan.soltani+ewah@gemmaanalytics.com
License: UNKNOWN
Platform: UNKNOWN
Classifier: Programming Language :: Python :: 3
Classifier: License :: OSI Approved :: MIT License
Requires-Python: >=3.6
Requires-Dist: avro
Requires-Dist: azure-storage-blob>=2.1.0
Requires-Dist: dbt-metabase<1.0
Requires-Dist: certifi==2025.1.31
Requires-Dist: croniter
Requires-Dist: facebook-business
Requires-Dist: google-ads>=25.2.0
Requires-Dist: google-cloud-bigquery
Requires-Dist: google-cloud-storage
Requires-Dist: googlemaps
Requires-Dist: gspread>=3.6
Requires-Dist: Jinja2
Requires-Dist: mailchimp3
Requires-Dist: msal
Requires-Dist: oauth2client
Requires-Dist: openpyxl
Requires-Dist: protobuf
Requires-Dist: psycopg2
Requires-Dist: pyairtable
Requires-Dist: pymongo
Requires-Dist: pymssql==2.3.1
Requires-Dist: pymysql
Requires-Dist: python-dateutil
Requires-Dist: pytz
Requires-Dist: pyyaml
Requires-Dist: recurly
Requires-Dist: selenium
Requires-Dist: simple-salesforce
Requires-Dist: snowflake-connector-python[pandas]
Requires-Dist: pyarrow
Requires-Dist: pandas
Requires-Dist: sqlalchemy
Requires-Dist: snowflake-sqlalchemy
Requires-Dist: sshtunnel>=0.2.2
Requires-Dist: stripe<13.0.0
Requires-Dist: virtualenv
Requires-Dist: yahoofinancials-gemma-analytics==1.23
Requires-Dist: yfinance
Provides-Extra: oracle
Requires-Dist: cx-Oracle; extra == "oracle"
